jobdec/__init__.py
jobdec/action.py
jobdec/app.py
jobdec/constants.py
jobdec/file_utils.py
jobdec/graph.py
jobdec/job_decorator.py
jobdec/scheduled_job.py
jobdec/scheduler.py
jobdec/utils.py
jobdec/static/style.css
jobdec-0.0.2.dist-info/LICENCE.txt
jobdec-0.0.2.dist-info/METADATA
jobdec-0.0.2.dist-info/WHEEL
jobdec-0.0.2.dist-info/top_level.txt
jobdec-0.0.2.dist-info/RECORD
